pangea_multipass_llama_index/__init__.py
pangea_multipass_llama_index/llama_index.py
pangea_multipass_llama_index/py.typed
pangea_multipass_llama_index-0.2.0.dist-info/METADATA
pangea_multipass_llama_index-0.2.0.dist-info/WHEEL
pangea_multipass_llama_index-0.2.0.dist-info/RECORD
