Metadata-Version: 2.1
Name: pangea-multipass-llama-index
Version: 0.2.0
Summary: Pangea Multipass authorization library for Llama Index
License: MIT
Author: Apurv Jawle
Author-email: apurv.jawle@pangea.cloud
Requires-Python: >=3.10,<3.13
Classifier: License :: OSI Approved :: MIT License
Classifier: Programming Language :: Python :: 3
Classifier: Programming Language :: Python :: 3.10
Classifier: Programming Language :: Python :: 3.11
Classifier: Programming Language :: Python :: 3.12
Requires-Dist: google-auth-oauthlib (>=1.2.1,<2.0.0)
Requires-Dist: llama-index (==0.11.11)
Requires-Dist: llama-index-embeddings-bedrock (==0.3.1)
Requires-Dist: llama-index-llms-bedrock (==0.2.1)
Requires-Dist: llama-index-readers-confluence (>=0.2.1,<0.3.0)
Requires-Dist: llama-index-readers-google (>=0.4.1,<0.5.0)
Requires-Dist: llama-index-readers-jira (>=0.3.1,<0.4.0)
Requires-Dist: pangea-multipass (==0.2.0)
Requires-Dist: pangea-sdk (>=5.1.0,<6.0.0)
